GummyFN/__init__.py
ZexFN-6.0.0.dist-info/LICENSE
ZexFN-6.0.0.dist-info/METADATA
ZexFN-6.0.0.dist-info/WHEEL
ZexFN-6.0.0.dist-info/entry_points.txt
ZexFN-6.0.0.dist-info/top_level.txt
ZexFN-6.0.0.dist-info/RECORD
