Metadata-Version: 2.1
Name: ZexFN
Version: 6.0.0
Summary: A Python package to get a old coding for fortnite
Home-page: UNKNOWN
Author: gummy.pts
Author-email: primalgummy@gmail.com
License: MIT
Platform: UNKNOWN
Classifier: License :: OSI Approved :: MIT License
Classifier: Programming Language :: Python :: 3
Classifier: Programming Language :: Python :: 3.7
Requires-Dist: requests
